groupick/__init__.py
groupick/py.typed
groupick-1.1.2.dist-info/LICENSE
groupick-1.1.2.dist-info/METADATA
groupick-1.1.2.dist-info/WHEEL
groupick-1.1.2.dist-info/RECORD
