Metadata-Version: 2.1
Name: groupick
Version: 1.1.2
Summary: Assign options to groups in the terminal with a simple GUI. Based on wong2's pick
Home-page: https://github.com/anafvana/groupick/
License: MIT
Keywords: terminal,gui,pick,group,assign
Author: Ana
Author-email: anafvana@gmail.com
Requires-Python: >=3.10
Classifier: License :: OSI Approved :: MIT License
Classifier: Programming Language :: Python :: 3
Classifier: Programming Language :: Python :: 3.10
Classifier: Programming Language :: Python :: 3.11
Requires-Dist: windows-curses (>=2.2.0,<3.0.0) ; sys_platform == "win32"
Project-URL: Repository, https://github.com/anafvana/groupick/
